asaas/__init__.py
asaas/customer.py
asaas/encoder.py
asaas/exceptions.py
asaas/payments.py
asaas/status.py
asaas/subscriptions.py
asaas/utils.py
asaas/webhooks.py
asaas_sdk_wlc-0.1.6.dist-info/LICENSE
asaas_sdk_wlc-0.1.6.dist-info/METADATA
asaas_sdk_wlc-0.1.6.dist-info/WHEEL
asaas_sdk_wlc-0.1.6.dist-info/top_level.txt
asaas_sdk_wlc-0.1.6.dist-info/RECORD
